README.rst
setup.cfg
setup.py
readable_content/__init__.py
readable_content/parser.py
readable_content.egg-info/PKG-INFO
readable_content.egg-info/SOURCES.txt
readable_content.egg-info/dependency_links.txt
readable_content.egg-info/requires.txt
readable_content.egg-info/top_level.txt