Metadata-Version: 1.1
Name: readable-content
Version: 0.1.2
Summary: Collect actual content of any article, blog, news, etc.
Home-page: https://github.com/nabinkhadka/readable-content
Author: Nabin Khadka
Author-email: nbnkhadka14@gmail.com
License: MIT license
Platform: UNKNOWN
Classifier: Development Status :: 3 - Alpha
Classifier: License :: OSI Approved :: MIT License
Classifier: Intended Audience :: Developers
Classifier: Operating System :: OS Independent
Classifier: Programming Language :: Python
Classifier: Programming Language :: Python :: 3
Classifier: Programming Language :: Python :: 3.7
Classifier: Programming Language :: Python :: 3.8
